xl30serial/__init__.py
xl30serial/scanningelectronmicroscope.py
xl30serial/xl30serial.py
pyxl30_tspspi-0.0.13.dist-info/LICENSE.md
pyxl30_tspspi-0.0.13.dist-info/METADATA
pyxl30_tspspi-0.0.13.dist-info/WHEEL
pyxl30_tspspi-0.0.13.dist-info/top_level.txt
pyxl30_tspspi-0.0.13.dist-info/RECORD
