Metadata-Version: 2.1
Name: pyxl30-tspspi
Version: 0.0.13
Summary: Control libraries and utilities for the XL30 ESEM (unofficial)
Home-page: https://github.com/tspspi/pyxl30
Author: Thomas Spielauer
Author-email: pypipackages01@tspi.at
Classifier: Programming Language :: Python :: 3
Classifier: License :: OSI Approved :: BSD License
Classifier: Operating System :: OS Independent
Requires-Python: >=3.6
License-File: LICENSE.md
Requires-Dist: pylabdevs-tspspi>=0.0.11
Requires-Dist: pyserial>=3.5
